{
    "time": {
        "cpu_time_user": "00:00:57.710",
        "cpu_time_system": "00:00:00.190",
        "runtime": "00:00:58.007",
        "cpu_time_iowait": "00:00:00.000"
    },
    "peak_resources": {
        "cpu_percent": 109.6,
        "memory_rss": "249MiB",
        "memory_vms": "264MiB",
        "threads": 1
    },
    "avg_resources": {
        "cpu_percent": 99.470883882149,
        "memory_rss": "233MiB",
        "memory_vms": "248MiB",
        "threads": 0.9982668977469671
    }
}